{
    "instruments": {
        "fishing_rod": {},
        "flint_and_steel": {},
        "shears": {},
        "axe": {},
        "pickaxe": {},
        "hoe": {},
        "shovel": {},
        "sword": {}
    },
    "list": {
        "air": {"mining": {"time": -1, "instruments": [], "blast_resistance": 0}},
        "amethyst": {"mining": {"time": 2, "instruments": ["pickaxe"], "blast_resistance": 1.5}},
        "bedrock": {"mining": {"time": -1, "instruments": [], "blast_resistance": 3600000}},
        "bone": {"mining": {"time": 4, "instruments": [], "blast_resistance": 2}},
        "clay": {"mining": {"time": 4, "instruments": ["shovel"], "blast_resistance": 0.5}},
        "cobblestone": {"mining": {"time": 5, "instruments": ["pickaxe"], "blast_resistance": 6}},
        "diamond": {"mining": {"time": 25, "instruments": ["pickaxe"], "instrument_boost": 8, "blast_resistance": 6}},
        "dirt": {"mining": {"time": 2, "instruments": ["shovel"], "blast_resistance": 0.5}},
        "dust": {"mining": {"time": 0, "instruments": [], "blast_resistance": 0.5}},
        "feather": {"mining": {"time": 0, "instruments": [], "blast_resistance": 0.2}},
        "food": {"mining": {"time": -1, "instruments": [], "blast_resistance": 0.2}},
        "glass": {"mining": {"time": 1, "instruments": [], "blast_resistance": 0.3}},
        "gold": {"mining": {"time": 5, "instruments": ["pickaxe"], "instrument_boost": 12, "blast_resistance": 6}},
        "gravel": {"mining": {"time": 2, "instruments": ["shovel"], "blast_resistance": 2.25}},
        "ice": {"mining": {"time": 5, "instruments": ["pickaxe"], "blast_resistance": 0.5}},
        "iron": {"mining": {"time": 10, "instruments": ["pickaxe"], "instrument_boost": 6, "blast_resistance": 6}},
        "lava": {"mining": {"time": -1, "instruments": [], "blast_resistance": 100}},
        "leather": {"mining": {"time": 1, "instruments": [], "blast_resistance": 0.5}},
        "leaves": {"mining": {"time": 2, "instruments": ["shovel", "hoe", "sword"], "blast_resistance": 0.2}},
        "netherite": {"mining": {"time": 250, "instruments": ["pickaxe"], "instrument_boost": 18, "blast_resistance": 1200}},
        "netherrack": {"mining": {"time": 2, "instruments": ["pickaxe"], "instrument_boost": 18, "blast_resistance": 0.4}},
        "obsidian": {"mining": {"time": 15, "instruments": ["pickaxe"], "blast_resistance": 1200}},
        "plant": {"mining": {"time": 0, "instruments": [], "blast_resistance": 0.2}},
        "powder": {"mining": {"time": 0, "instruments": [], "blast_resistance": 0.5}},
        "quartz": {"mining": {"time": 7, "instruments": ["pickaxe"], "blast_resistance": 0.8}},
        "sand": {"mining": {"time": 2, "instruments": ["shovel"], "blast_resistance": 0.5}},
        "snow": {"mining": {"time": 2, "instruments": ["shovel"], "blast_resistance": 1}},
        "stone": {"mining": {"time": 7, "instruments": ["pickaxe"], "instrument_boost": 4, "blast_resistance": 6}},
        "terracota": {"mining": {"time": 5, "instruments": ["pickaxe"], "blast_resistance": 4.2}},
        "water": {"mining": {"time": -1, "instruments": [], "blast_resistance": 100}},
        "wood": {"mining": {"time": 4, "instruments": ["axe"], "instrument_boost": 2, "blast_resistance": 2}},
        "wool": {"mining": {"time": 2, "instruments": ["shears"], "blast_resistance": 0.8}},
        "web": {"mining": {"time": 1, "instruments": ["shears", "sword"], "blast_resistance": 0.8}},
        "cactus": {"mining": {"time": 1, "instruments": [], "blast_resistance": 0.8}}
    }
}